p2a/__init__.py
p2a/model.py
p2a/tests/test_model.py
p2a-0.1.1.dist-info/METADATA
p2a-0.1.1.dist-info/WHEEL
p2a-0.1.1.dist-info/licenses/LICENSE
p2a-0.1.1.dist-info/RECORD
