Metadata-Version: 2.4
Name: p2a
Version: 0.1.1
Summary: pydantic models to argparse CLIs
Project-URL: Repository, https://github.com/python-project-templates/p2a
Project-URL: Homepage, https://github.com/python-project-templates/p2a
Author-email: the p2a authors <t.paine154@gmail.com>
License: Apache-2.0
License-File: LICENSE
Keywords: argparse,cli,command-line,models,pydantic,validation
Classifier: Development Status :: 3 - Alpha
Classifier: Programming Language :: Python
Classifier: Programming Language :: Python :: 3
Classifier: Programming Language :: Python :: 3.10
Classifier: Programming Language :: Python :: 3.11
Classifier: Programming Language :: Python :: 3.12
Classifier: Programming Language :: Python :: 3.13
Classifier: Programming Language :: Python :: 3.14
Classifier: Programming Language :: Python :: Implementation :: CPython
Classifier: Programming Language :: Python :: Implementation :: PyPy
Requires-Python: >=3.10
Requires-Dist: pkn<0.4,>=0.3
Provides-Extra: develop
Requires-Dist: build; extra == 'develop'
Requires-Dist: bump-my-version; extra == 'develop'
Requires-Dist: check-manifest; extra == 'develop'
Requires-Dist: codespell<2.5,>=2.4; extra == 'develop'
Requires-Dist: hatchling; extra == 'develop'
Requires-Dist: mdformat-tables>=1; extra == 'develop'
Requires-Dist: mdformat<1.1,>=0.7.22; extra == 'develop'
Requires-Dist: pytest; extra == 'develop'
Requires-Dist: pytest-cov; extra == 'develop'
Requires-Dist: ruff<0.15,>=0.9; extra == 'develop'
Requires-Dist: twine; extra == 'develop'
Requires-Dist: uv; extra == 'develop'
Requires-Dist: wheel; extra == 'develop'
